disjotter/__init__.py
disjotter/__main__.py
disjotter/backend/__init__.py
disjotter/backend/container/__init__.py
disjotter/backend/container/creator.py
disjotter/backend/handlers/__init__.py
disjotter/backend/handlers/base_handler.py
disjotter/backend/handlers/build_handler.py
disjotter/backend/handlers/command_handler.py
disjotter/backend/handlers/environment_handler.py
disjotter/backend/handlers/inspect_handler.py
disjotter/backend/handlers/template_handler.py
disjotter/backend/templates/form.html
disjotter/backend/templates/inspector.html
disjotter/frontend/index.js
disjotter/frontend/modal.js
disjotter/frontend/util.js
disjotter/helper/__init__.py
disjotter/helper/handlers.py
disjotter/helper/helper_requirements.txt
disjotter/helper/notebook_runner.py
disjotter/helper/util.py
disjotter/inspection/__init__.py
disjotter/inspection/_base.py
disjotter/inspection/python3.py
DisJotter-1.0.5.dist-info/LICENSE
DisJotter-1.0.5.dist-info/METADATA
DisJotter-1.0.5.dist-info/WHEEL
DisJotter-1.0.5.dist-info/top_level.txt
DisJotter-1.0.5.dist-info/RECORD
