Metadata-Version: 2.1
Name: DisJotter
Version: 1.0.5
Summary: DisJotter allows the user to interactively create a Docker image from a Jupyter Notebook.
Home-page: https://github.com/WilcoKruijer/DisJotter
Author: Wilco Kruijer
Author-email: wilcokruijer@gmail.com
License: UNKNOWN
Platform: UNKNOWN
Classifier: Programming Language :: Python :: 3
Classifier: License :: OSI Approved :: Apache Software License
Classifier: Operating System :: OS Independent
Requires-Python: >=3.6
Requires-Dist: docker (>=4.2.0)
Requires-Dist: pigar (>=0.10.0)
